{
  "gitSyncId": "67229180c256c75afd37fa08_750ba787-1c2c-4d23-a9de-f4cff7c67b5a",
  "id": "Podsumowanie_pdf_polski_z_rabatami_pobierz.BuildPDF",
  "pluginId": "js-plugin",
  "pluginType": "JS",
  "unpublishedAction": {
    "actionConfiguration": {
      "encodeParamsToggle": true,
      "jsArguments": [],
      "paginationType": "NONE",
      "timeoutInMillisecond": 10000
    },
    "collectionId": "Podsumowanie_pdf_polski_z_rabatami_pobierz",
    "confirmBeforeExecute": false,
    "datasource": {
      "isAutoGenerated": false,
      "name": "UNUSED_DATASOURCE",
      "pluginId": "js-plugin"
    },
    "dynamicBindingPathList": [
      {
        "key": "body"
      }
    ],
    "executeOnLoad": false,
    "fullyQualifiedName": "pdf_polski_z_rabatami_pobierz.BuildPDF",
    "name": "BuildPDF",
    "pageId": "Podsumowanie",
    "userSetOnLoad": false
  }
}